hankai/__init__.py
hankai/aws/__init__.py
hankai/aws/bin/__init__.py
hankai/aws/bin/codeartifact_env_setup.py
hankai/aws/bin/codeartifact_env_setup_argparse.py
hankai/aws/bin/ecr_docker.py
hankai/aws/bin/ecr_docker_argparse.py
hankai/aws/bin/iam_mfa_argparse.py
hankai/aws/bin/iam_mfa_config.py
hankai/aws/scale/__init__.py
hankai/aws/scale/env_attr.py
hankai/aws/scale/base/__init__.py
hankai/aws/scale/base/scale.py
hankai/aws/scale/base/scale_by.py
hankai/aws/scale/by/__init__.py
hankai/aws/scale/by/sqs.py
hankai/aws/scale/composite/__init__.py
hankai/aws/scale/composite/ec2asg_ecs_by_sqs.py
hankai/aws/scale/ec2/__init__.py
hankai/aws/scale/ec2/asg_by_sqs.py
hankai/aws/scale/ecs/__init__.py
hankai/aws/scale/ecs/by_sqs.py
hankai/aws/sdk/__init__.py
hankai/aws/sdk/environment.py
hankai/aws/sdk/servicer.py
hankai/aws/sdk/session.py
hankai/aws/service/__init__.py
hankai/aws/service/codeartifact/__init__.py
hankai/aws/service/codeartifact/codeartifact.py
hankai/aws/service/ec2/__init__.py
hankai/aws/service/ec2/auto_scaling.py
hankai/aws/service/ecr/__init__.py
hankai/aws/service/ecr/elastic_container_registry.py
hankai/aws/service/ecs/__init__.py
hankai/aws/service/ecs/elastic_container_service.py
hankai/aws/service/s3/__init__.py
hankai/aws/service/s3/simple_storage_service.py
hankai/aws/service/sqs/__init__.py
hankai/aws/service/sqs/scale.py
hankai/aws/service/sqs/simple_queue_service.py
hank_ai_aws-3.2.3.dist-info/METADATA
hank_ai_aws-3.2.3.dist-info/WHEEL
hank_ai_aws-3.2.3.dist-info/entry_points.txt
hank_ai_aws-3.2.3.dist-info/namespace_packages.txt
hank_ai_aws-3.2.3.dist-info/top_level.txt
hank_ai_aws-3.2.3.dist-info/RECORD
